arris_tg3442_reboot/__init__.py
arris_tg3442_reboot/__main__.py
arris_tg3442_reboot/firmware.py
arris_tg3442_reboot/reboot.py
arris_tg3442_reboot-0.7.data/scripts/reboot.py
arris_tg3442_reboot-0.7.dist-info/LICENSE
arris_tg3442_reboot-0.7.dist-info/METADATA
arris_tg3442_reboot-0.7.dist-info/WHEEL
arris_tg3442_reboot-0.7.dist-info/top_level.txt
arris_tg3442_reboot-0.7.dist-info/RECORD
