Metadata-Version: 2.1
Name: arris-tg3442-reboot
Version: 0.7
Summary: Reboot your Arris TG-3442 router via cli
Home-page: https://github.com/diveflo/arris-tg3442-reboot
Author: Florian Gabsteiger
Author-email: florian.g@me.com
License: UNKNOWN
Platform: UNKNOWN
Classifier: Programming Language :: Python :: 3
Classifier: License :: OSI Approved :: Apache Software License
Classifier: Operating System :: OS Independent
Requires-Python: >=3.6
